mypackage/__init__.py
mypackage/decorators.py
mypackage/descriptors.py
mypackage/generators.py
mypackage/iterators.py
mypackage_den-0.1.0.dist-info/METADATA
mypackage_den-0.1.0.dist-info/WHEEL
mypackage_den-0.1.0.dist-info/top_level.txt
mypackage_den-0.1.0.dist-info/RECORD
